{
  "version": 1,
  "rev": 76,
  "cursor": "tick-76",
  "data": {
    "perPr": {
      "1217": {
        "lastSha": "b6c0edddbac4e6ccaab9f543aaca1b3672c21ccc",
        "attempts": 1,
        "stuck": false,
        "lastActionAt": "2026-05-01T16:30:53Z"
      },
      "1227": {
        "lastSha": "37719014e5a0de3601d0770425e378c06473d305",
        "attempts": 2,
        "stuck": true,
        "lastActionAt": "2026-05-01T13:00:00Z"
      },
      "1266": {
        "lastSha": "57b2556598b43fd4d0b922f5fd0fbdf373e03bdb",
        "attempts": 2,
        "stuck": true,
        "lastActionAt": "2026-05-01T13:00:00Z"
      },
      "1272": {
        "lastSha": "d607b2920f6d9368f4e274cfe93ec37a7f1831b5",
        "attempts": 2,
        "stuck": true,
        "lastActionAt": "2026-05-01T13:00:00Z"
      },
      "1285": {
        "lastSha": "98568e52b58cdbb8d15d680be1c80ed5217c316c",
        "attempts": 0,
        "stuck": false,
        "lastActionAt": null
      },
      "1364": {
        "lastSha": "dc659c9dd9eeab3be01687bc22461f48a9976f75",
        "attempts": 2,
        "stuck": true,
        "lastActionAt": "2026-05-01T13:00:00Z"
      },
      "1366": {
        "lastSha": "35e97738e331d3e083dae44b070d5551679f6472",
        "attempts": 2,
        "stuck": true,
        "lastActionAt": "2026-05-01T13:00:00Z"
      },
      "1374": {
        "lastSha": "93284a397b17f7ce54bf3af11797ccabcce45884",
        "attempts": 0,
        "stuck": false,
        "lastActionAt": null
      },
      "1375": {
        "lastSha": "585c6f74347032aec7913b3d49cca9e85274bd2b",
        "attempts": 1,
        "stuck": false,
        "lastActionAt": "2026-05-01T19:37:44Z"
      },
      "1376": {
        "lastSha": "b223d8f2da07511085947f89c5701b72b33c0fd0",
        "attempts": 0,
        "stuck": false,
        "lastActionAt": null
      },
      "1377": {
        "lastSha": "4cf8b6cb8da107415e149127b78ef4a61075e8dc",
        "attempts": 0,
        "stuck": false,
        "lastActionAt": null
      },
      "1381": {
        "lastSha": "6d544ffac2bb95d49523cabd0016bf83f8046896",
        "attempts": 0,
        "stuck": false,
        "lastActionAt": null
      },
      "1383": {
        "lastSha": "2440e1a0d4120ab2fac07970ccd1def483e8a0b8",
        "attempts": 0,
        "stuck": false,
        "lastActionAt": null
      },
      "1384": {
        "lastSha": "274a07ce321b03f032e0fb6bd26380120858dd3a",
        "attempts": 1,
        "stuck": false,
        "lastActionAt": "2026-05-01T14:55:00Z"
      }
    }
  },
  "done": false
}
