{
  "type": "lesson",
  "name": "issue-1678",
  "title": "Issue #1678: \u05d4\u05d5\u05e1\u05e4\u05ea \u05d4\u05de\u05dc\u05e6\u05d4 \u05dc\u05e9\u05d9\u05e2\u05d5\u05e8 \u05e2\u05d5\u05e7\u05d1 \u05d1\u05d3\u05e3 \u05e1\u05d9\u05d5\u05dd \u05e9\u05d9\u05e2\u05d5\u05e8",
  "hook": "\u05d4\u05d5\u05e1\u05e4\u05ea \u05d4\u05de\u05dc\u05e6\u05d4 \u05dc\u05e9\u05d9\u05e2\u05d5\u05e8 \u05e2\u05d5\u05e7\u05d1 \u05d1\u05d3\u05e3 \u05e1\u05d9\u05d5\u05dd \u05e9\u05d9\u05e2\u05d5\u05e8 \u2014 closed 2026-05-20 (COMPLETED)",
  "body": "**Issue:** [https://github.com/A-Guy-educ/A-Guy/issues/1678](https://github.com/A-Guy-educ/A-Guy/issues/1678)\n**Reporter:** @korenguy123\n**Closed:** 2026-05-20T14:07:00Z (COMPLETED)\n\n## Title\n\u05d4\u05d5\u05e1\u05e4\u05ea \u05d4\u05de\u05dc\u05e6\u05d4 \u05dc\u05e9\u05d9\u05e2\u05d5\u05e8 \u05e2\u05d5\u05e7\u05d1 \u05d1\u05d3\u05e3 \u05e1\u05d9\u05d5\u05dd \u05e9\u05d9\u05e2\u05d5\u05e8\n\n## Summary (first section of issue body)\n# New Feature: \u05d4\u05d5\u05e1\u05e4\u05ea \u05d4\u05de\u05dc\u05e6\u05d4 \u05dc\u05e9\u05d9\u05e2\u05d5\u05e8 \u05e2\u05d5\u05e7\u05d1 \u05d1\u05d3\u05e3 \u05e1\u05d9\u05d5\u05dd \u05e9\u05d9\u05e2\u05d5\u05e8\n",
  "source": "job:issue-learner",
  "ts": "2026-05-20T14:11:21Z",
  "links": []
}