{
  "taskId": "13",
  "taskType": "pr",
  "target": "dependabot/npm_and_yarn/mathjs-15.2.0",
  "outcome": "success",
  "exitCode": 0,
  "reason": "CI failure was environmental (stale node_modules on runner); code is correct and all tests pass locally with mathjs 15.2.0",
  "prUrl": "https://github.com/A-Guy-educ/A-Guy-Web/pull/13",
  "runUrl": "https://github.com/A-Guy-educ/A-Guy-Web/actions/runs/27201507885",
  "filesTouched": [],
  "sessionLog": ".kody/sessions/todo.jsonl",
  "startedAt": "2026-06-10T19:50:00Z",
  "finishedAt": "2026-06-10T20:04:28Z"
}
